gslconsts/__about__.py
gslconsts/__init__.py
gslconsts/consts.py
gslconsts/math.py
gslconsts-1.1.2.dist-info/LICENSE.txt
gslconsts-1.1.2.dist-info/METADATA
gslconsts-1.1.2.dist-info/WHEEL
gslconsts-1.1.2.dist-info/top_level.txt
gslconsts-1.1.2.dist-info/RECORD
