Metadata-Version: 2.1
Name: gslconsts
Version: 1.1.2
Summary: Python project GNU Scientific Library (GSL) constants
Home-page: https://github.com/mbradle/gslconsts
Author: Clemson University
Author-email: mbradle@g.clemson.edu
License: GPLv3+
Project-URL: Bug Reports, https://github.com/mbradle/gslconsts/issues
Project-URL: Source, https://github.com/mbradle/gslconsts/
Keywords: astronomy nuclear astrophysics
Classifier: Development Status :: 3 - Alpha
Classifier: Intended Audience :: Science/Research
Classifier: Topic :: Scientific/Engineering :: Astronomy
Classifier: License :: OSI Approved :: GNU General Public License v3 or later (GPLv3+)
Classifier: Programming Language :: Python :: 3
License-File: LICENSE.txt
Provides-Extra: dev
Requires-Dist: check-manifest ; extra == 'dev'
Provides-Extra: test
Requires-Dist: coverage ; extra == 'test'
